weworkbot/__init__.py
weworkbot/bot.py
weworkbot/bot_mgr.py
weworkbot-0.3.0.dist-info/LICENSE
weworkbot-0.3.0.dist-info/METADATA
weworkbot-0.3.0.dist-info/WHEEL
weworkbot-0.3.0.dist-info/top_level.txt
weworkbot-0.3.0.dist-info/RECORD
